madyel/phpbb.py
madyel/config/__init__.py
madyel/config/configure.py
phpbb_topic_post-0.9.dist-info/LICENSE.txt
phpbb_topic_post-0.9.dist-info/METADATA
phpbb_topic_post-0.9.dist-info/WHEEL
phpbb_topic_post-0.9.dist-info/top_level.txt
phpbb_topic_post-0.9.dist-info/RECORD
