Metadata-Version: 2.1
Name: phpbb-topic-post
Version: 0.9
Summary: PhpBB add topic and post
Home-page: https://github.com/madyel/phpbb
Author: MaDyEl
Author-email: madyel83@tutanota.com
License: MIT
Platform: UNKNOWN
License-File: LICENSE.txt
Requires-Dist: bcrypt (==3.2.0)
Requires-Dist: cffi (==1.15.0)
Requires-Dist: cryptography (==36.0.2)
Requires-Dist: paramiko (==2.10.3)
Requires-Dist: pycparser (==2.21)
Requires-Dist: PyMySQL (==1.0.2)
Requires-Dist: PyNaCl (==1.5.0)
Requires-Dist: six (==1.16.0)
Requires-Dist: sshtunnel (==0.4.0)
